subdeloc_tools/__init__.py
subdeloc_tools/subtools.py
subdeloc_tools/test.py
subdeloc_tools/common/__init__.py
subdeloc_tools/common/decorators/__init__.py
subdeloc_tools/common/decorators/decorators.py
subdeloc_tools/common/types/__init__.py
subdeloc_tools/common/types/types.py
subdeloc_tools/common/utils/__init__.py
subdeloc_tools/common/utils/logger_config.py
subdeloc_tools/modules/__init__.py
subdeloc_tools/modules/extract_subs.py
subdeloc_tools/modules/honorific_fixer.py
subdeloc_tools/modules/honorific_utils.py
subdeloc_tools/modules/merger.py
subdeloc_tools/modules/pairsubs.py
subdeloc_tools/modules/shift_subs.py
subdeloc_tools/samples/honorifics.json
tests/__init__.py
tests/test_honorific_fixer.py
tests/test_honorific_utils.py
tests/test_pairsubs.py
tests/test_subtools.py
tests/constants/__init__.py
tests/constants/pairsubs.py
tests/constants/subtools.py
subdeloc_tools-0.9.12.dist-info/LICENSE
subdeloc_tools-0.9.12.dist-info/METADATA
subdeloc_tools-0.9.12.dist-info/WHEEL
subdeloc_tools-0.9.12.dist-info/top_level.txt
subdeloc_tools-0.9.12.dist-info/RECORD
