Metadata-Version: 2.1
Name: subdeloc-tools
Version: 0.9.12
Summary: Subtitles delocalizer tools.
Home-page: https://github.com/EfronC/subdeloc_tools
Author: Efrain Cardenas
Author-email: 
License: UNKNOWN
Platform: UNKNOWN
Classifier: Programming Language :: Python :: 3
Classifier: License :: OSI Approved :: GNU General Public License v3 (GPLv3)
Classifier: Operating System :: OS Independent
Requires-Python: >=3.8
License-File: LICENSE
Requires-Dist: appdirs
Requires-Dist: modify-subs (>=0.5.2)
Requires-Dist: pysubs2
